{
  "version": "1.1.1",
  "windows": {
    "main": {
      "main": true,
      "url": "app://editor/index.html",
      "windowType": "dockable",
      "x": -8,
      "y": -8,
      "width": 1382,
      "height": 744,
      "layout": {
        "children": [
          {
            "children": [
              {
                "active": 0,
                "children": [
                  "hierarchy"
                ],
                "height": 300,
                "type": "panel",
                "width": 204
              },
              {
                "active": 0,
                "children": [
                  "assets"
                ],
                "height": 313,
                "type": "panel",
                "width": 204
              }
            ],
            "height": 616,
            "type": "dock-v",
            "width": 204
          },
          {
            "active": 0,
            "children": [
              "inspector"
            ],
            "height": 616,
            "type": "panel",
            "width": 304
          },
          {
            "children": [
              {
                "active": 0,
                "children": [
                  "scene"
                ],
                "height": 155,
                "type": "panel",
                "width": 845.984375
              },
              {
                "active": 0,
                "children": [
                  "console",
                  "timeline"
                ],
                "height": 458,
                "type": "panel",
                "width": 845.984375
              }
            ],
            "height": 616,
            "type": "dock-v",
            "width": 845.984375
          }
        ],
        "type": "dock-h"
      },
      "panels": [
        "hierarchy",
        "inspector",
        "console",
        "timeline",
        "assets",
        "scene"
      ]
    }
  },
  "panels": {
    "preferences": {
      "x": -8,
      "y": -8,
      "width": 1382,
      "height": 744
    },
    "project-settings": {
      "x": 385,
      "y": 84,
      "width": 596,
      "height": 559
    }
  }
}